specdal/__init__.py
specdal/collection.py
specdal/operator.py
specdal/reader.py
specdal/spectrum.py
specdal/gui/__init__.py
specdal/gui/collection_manager.py
specdal/gui/gui.py
specdal/gui/viewer.py
specdal/utils/__init__.py
specdal/utils/misc.py
specdal/utils/reader_utils.py
specdal-0.2.1.data/scripts/specdal_info
specdal-0.2.1.data/scripts/specdal_pipeline
specdal-0.2.1.dist-info/DESCRIPTION.rst
specdal-0.2.1.dist-info/METADATA
specdal-0.2.1.dist-info/RECORD
specdal-0.2.1.dist-info/WHEEL
specdal-0.2.1.dist-info/metadata.json
specdal-0.2.1.dist-info/top_level.txt
