Metadata-Version: 2.0
Name: specdal
Version: 0.2.1
Summary: Package for processing spectroscopy data
Home-page: https://github.com/EnSpec/SpecDAL/
Author: Young Lee
Author-email: ylee546@wisc.edu
License: MIT
Platform: UNKNOWN
Classifier: Development Status :: 3 - Alpha
Classifier: Intended Audience :: Science/Research
Classifier: Topic :: Scientific/Engineering :: Atmospheric Science
Classifier: Programming Language :: Python :: 3
Requires-Python: >=3
Requires-Dist: numpy
Requires-Dist: pandas
Requires-Dist: matplotlib
Requires-Dist: scipy
